advancedfirebase/__init__.py
advancedfirebase/db.py
advancedfirebase/myfunctions.py
advancedfirebase-1.1.4.dist-info/METADATA
advancedfirebase-1.1.4.dist-info/WHEEL
advancedfirebase-1.1.4.dist-info/top_level.txt
advancedfirebase-1.1.4.dist-info/RECORD
