Metadata-Version: 2.1
Name: advancedfirebase
Version: 1.1.4
Summary: Advanced Firebase
Home-page: UNKNOWN
Author: Artem Lukashenko
License: MIT
Platform: UNKNOWN
Requires-Dist: firebase-admin
